docs/source/conf.py
skbase/__init__.py
skbase/_exceptions.py
skbase/_nopytest_tests.py
skbase/base/__init__.py
skbase/base/_base.py
skbase/base/_meta.py
skbase/base/_tagmanager.py
skbase/base/_pretty_printing/__init__.py
skbase/base/_pretty_printing/_object_html_repr.py
skbase/base/_pretty_printing/_pprint.py
skbase/lookup/__init__.py
skbase/lookup/_lookup.py
skbase/lookup/tests/__init__.py
skbase/lookup/tests/test_lookup.py
skbase/testing/__init__.py
skbase/testing/test_all_objects.py
skbase/testing/utils/__init__.py
skbase/testing/utils/_conditional_fixtures.py
skbase/testing/utils/_dependencies.py
skbase/testing/utils/deep_equals.py
skbase/testing/utils/inspect.py
skbase/testing/utils/tests/__init__.py
skbase/testing/utils/tests/test_check_dependencies.py
skbase/testing/utils/tests/test_deep_equals.py
skbase/tests/__init__.py
skbase/tests/conftest.py
skbase/tests/test_base.py
skbase/tests/test_baseestimator.py
skbase/tests/test_exceptions.py
skbase/tests/test_meta.py
skbase/tests/mock_package/__init__.py
skbase/tests/mock_package/test_mock_package.py
skbase/utils/__init__.py
skbase/utils/_check.py
skbase/utils/_iter.py
skbase/utils/_nested_iter.py
skbase/utils/_utils.py
skbase/utils/deep_equals.py
skbase/utils/dependencies/__init__.py
skbase/utils/dependencies/_dependencies.py
skbase/utils/tests/__init__.py
skbase/utils/tests/test_check.py
skbase/utils/tests/test_iter.py
skbase/utils/tests/test_nested_iter.py
skbase/utils/tests/test_utils.py
skbase/validate/__init__.py
skbase/validate/_named_objects.py
skbase/validate/_types.py
skbase/validate/tests/__init__.py
skbase/validate/tests/test_iterable_named_objects.py
skbase/validate/tests/test_type_validations.py
skbase-0.4.6.dist-info/LICENSE
skbase-0.4.6.dist-info/METADATA
skbase-0.4.6.dist-info/WHEEL
skbase-0.4.6.dist-info/top_level.txt
skbase-0.4.6.dist-info/zip-safe
skbase-0.4.6.dist-info/RECORD
