Metadata-Version: 2.1
Name: skbase
Version: 0.4.6
Summary: Base classes for sklearn-like parametric objects
Author-email: sktime developers <sktime.toolbox@gmail.com>
Maintainer: Franz Király
Maintainer-email: sktime developers <sktime.toolbox@gmail.com>
License: BSD 3-Clause License
Project-URL: homepage, https://github.com/sktime/skbase
Project-URL: repository, https://github.com/sktime/skbase
Project-URL: documentation, https://github.com/sktime/skbase
Project-URL: download, https://pypi.org/project/skbase/#files
Keywords: data-science,machine-learning,scikit-learn
Classifier: Intended Audience :: Science/Research
Classifier: Intended Audience :: Developers
Classifier: License :: OSI Approved :: BSD License
Classifier: Programming Language :: Python
Classifier: Topic :: Software Development
Classifier: Topic :: Scientific/Engineering
Classifier: Operating System :: Microsoft :: Windows
Classifier: Operating System :: POSIX
Classifier: Operating System :: Unix
Classifier: Operating System :: MacOS
Classifier: Programming Language :: Python :: 3.7
Classifier: Programming Language :: Python :: 3.8
Classifier: Programming Language :: Python :: 3.9
Classifier: Programming Language :: Python :: 3.10
Classifier: Programming Language :: Python :: 3.11
Requires-Python: <3.12,>=3.7
License-File: LICENSE
Provides-Extra: all_extras
Requires-Dist: numpy ; extra == 'all_extras'
Requires-Dist: pandas ; extra == 'all_extras'
Provides-Extra: binder
Requires-Dist: jupyter ; extra == 'binder'
Provides-Extra: dev
Requires-Dist: scikit-learn (>=0.24.0) ; extra == 'dev'
Requires-Dist: pre-commit ; extra == 'dev'
Requires-Dist: pytest ; extra == 'dev'
Requires-Dist: pytest-cov ; extra == 'dev'
Provides-Extra: docs
Requires-Dist: jupyter ; extra == 'docs'
Requires-Dist: myst-parser ; extra == 'docs'
Requires-Dist: nbsphinx (>=0.8.6) ; extra == 'docs'
Requires-Dist: numpydoc ; extra == 'docs'
Requires-Dist: pydata-sphinx-theme ; extra == 'docs'
Requires-Dist: sphinx-issues (==1.2.0) ; extra == 'docs'
Requires-Dist: sphinx-gallery (==0.6.0) ; extra == 'docs'
Requires-Dist: sphinx-panels ; extra == 'docs'
Requires-Dist: sphinx-design (==0.3.0) ; extra == 'docs'
Requires-Dist: sphinx (==4.1.1) ; extra == 'docs'
Requires-Dist: tabulate ; extra == 'docs'
Provides-Extra: linters
Requires-Dist: mypy ; extra == 'linters'
Requires-Dist: isort ; extra == 'linters'
Requires-Dist: flake8 ; extra == 'linters'
Requires-Dist: black ; extra == 'linters'
Requires-Dist: pydocstyle ; extra == 'linters'
Requires-Dist: nbqa ; extra == 'linters'
Requires-Dist: flake8-bugbear ; extra == 'linters'
Requires-Dist: flake8-builtins ; extra == 'linters'
Requires-Dist: flake8-quotes ; extra == 'linters'
Requires-Dist: flake8-comprehensions ; extra == 'linters'
Requires-Dist: pandas-vet ; extra == 'linters'
Requires-Dist: flake8-print ; extra == 'linters'
Requires-Dist: pep8-naming ; extra == 'linters'
Requires-Dist: doc8 ; extra == 'linters'
Provides-Extra: test
Requires-Dist: pytest ; extra == 'test'
Requires-Dist: coverage ; extra == 'test'
Requires-Dist: pytest-cov ; extra == 'test'
Requires-Dist: safety ; extra == 'test'
Requires-Dist: numpy ; extra == 'test'
Requires-Dist: scipy ; extra == 'test'
Requires-Dist: pandas ; extra == 'test'
Requires-Dist: scikit-learn (>=0.24.0) ; extra == 'test'
